tpch_runner/__init__.py
tpch_runner/_version.py
tpch_runner/config.py
tpch_runner/meta.py
tpch_runner/commands/__init__.py
tpch_runner/commands/base_commands.py
tpch_runner/commands/db_commands.py
tpch_runner/commands/power_commands.py
tpch_runner/commands/result_commands.py
tpch_runner/commands/run_commands.py
tpch_runner/commands/utils.py
tpch_runner/tpch/__init__.py
tpch_runner/tpch/injection.py
tpch_runner/tpch/databases/__init__.py
tpch_runner/tpch/databases/base.py
tpch_runner/tpch/databases/duckdb.py
tpch_runner/tpch/databases/mysqldb.py
tpch_runner/tpch/databases/parser.py
tpch_runner/tpch/databases/pgdb.py
tpch_runner/tpch/databases/rapidsdb.py
tpch_runner/tpch/databases/results.py
tpch_runner-1.0.1.dist-info/LICENSE
tpch_runner-1.0.1.dist-info/METADATA
tpch_runner-1.0.1.dist-info/WHEEL
tpch_runner-1.0.1.dist-info/entry_points.txt
tpch_runner-1.0.1.dist-info/top_level.txt
tpch_runner-1.0.1.dist-info/RECORD
