Metadata-Version: 2.2
Name: tpch_runner
Version: 1.0.1
Summary: A tool for running TPC-H benchmarks and analyzing results.
Author-email: Robert Li <lgprobert@gmail.com>
License: MIT
Project-URL: Homepage, https://github.com/lgprobert/tpch_runner
Keywords: TPC-H,benchmark,database,performance
Classifier: License :: OSI Approved :: MIT License
Classifier: Programming Language :: Python :: 3.7
Classifier: Programming Language :: Python :: 3.8
Classifier: Programming Language :: Python :: 3.9
Classifier: Programming Language :: Python :: 3.10
Classifier: Programming Language :: Python :: Implementation :: CPython
Classifier: Programming Language :: Python :: Implementation :: PyPy
Classifier: Topic :: Database
Classifier: Topic :: Software Development :: Libraries :: Python Modules
Requires-Python: >=3.7
License-File: LICENSE
Requires-Dist: click>=8.1.0
Requires-Dist: rich-click
Requires-Dist: duckdb
Requires-Dist: matplotlib>=3.10.0
Requires-Dist: psycopg2>=2.9
Requires-Dist: PyMySQL>=1.1
Requires-Dist: pyrdpdb>=4.1.0
Requires-Dist: pandas
Requires-Dist: sqlalchemy>=2.0
Requires-Dist: sqlglot>=26.3.8
Requires-Dist: sqlparse>=0.5.0
Requires-Dist: tabulate
Provides-Extra: dev
Requires-Dist: pytest; extra == "dev"
Requires-Dist: pytest-stubs; extra == "dev"
Requires-Dist: pytest-mock; extra == "dev"
Requires-Dist: pandas-stubs; extra == "dev"
Requires-Dist: types-PyMySQL; extra == "dev"
Requires-Dist: types-psycopg2; extra == "dev"
